pylabnotebook-0.3.1.dist-info/METADATA
pylabnotebook-0.3.1.dist-info/WHEEL
pylabnotebook-0.3.1.dist-info/entry_points.txt
pylabnotebook/.DS_Store
pylabnotebook/LICENSE
pylabnotebook/__init__.py
pylabnotebook/cli.py
pylabnotebook/exceptions.py
pylabnotebook/export.py
pylabnotebook/init.py
pylabnotebook/templates/base.html
pylabnotebook/templates/rc
pylabnotebook/templates/style.css
pylabnotebook/version.py
pylabnotebook-0.3.1.dist-info/RECORD
