Metadata-Version: 2.1
Name: pylabnotebook
Version: 0.3.1
Summary: This package provides functions to write an automated labnotebook using git.
Keywords: git,notebook,track,history,log
Author-Email: Matteo Miotto <miotsdata@gmail.com>
License: MIT
Classifier: Programming Language :: Python :: 3
Classifier: License :: OSI Approved :: MIT License
Classifier: Operating System :: OS Independent
Project-URL: Homepage, https://github.com/mmiots9/pylabnotebook
Project-URL: Issues, https://github.com/mmiots9/pylabnotebook/issues
Requires-Python: >=3.7
Requires-Dist: setuptools>=72.1.0
Requires-Dist: argparse>=1.4.0
Requires-Dist: sphinx-rtd-theme>=2.0.0
Requires-Dist: myst-parser>=4.0.0
Requires-Dist: Jinja2>=3.1.4
